{
  "text": "==378==ERROR: AddressSanitizer: heap-use-after-free on address 0xac80d400 at pc 0xaf036288 bp 0xac9ff740 sp 0xac9ff30c\n\n\nREAD of size 2 at 0xac80d400 thread T27 (NuCachedSource2)\n\n    #0 0xaf036287 in strlen\n\n    #1 0xaef0a307 in __strlen_chk bionic/libc/bionic/fortify.cpp:313:16\n\n    #2 0xaf9f961d in strlen bionic/libc/include/string.h:325:12\n    #3 0xaf9f961d in android::AString::setTo(char const*) frameworks/av/media/libstagefright/foundation/AString.cpp:112\n    #4 0xaf9f961d in android::AString::AString(char const*) frameworks/av/media/libstagefright/foundation/AString.cpp:50\n\n    #5 0xaf755afb in android::MediaHTTP::connect(char const*, android::KeyedVector<android::String8, android::String8> const*, long long) frameworks/av/media/libstagefright/http/MediaHTTP.cpp:69:44\n\n    #6 0xaf755e23 in android::MediaHTTP::reconnectAtOffset(long long) frameworks/av/media/libstagefright/http/MediaHTTP.cpp:148:12\n\n    #7 0xaf757563 in android::NuCachedSource2::fetchInternal() frameworks/av/media/libstagefright/NuCachedSource2.cpp:339:13\n\n    #8 0xaf757253 in android::NuCachedSource2::onFetch() frameworks/av/media/libstagefright/NuCachedSource2.cpp:415:9\n\n    #9 0xaf758419 in android::AHandlerReflector<android::NuCachedSource2>::onMessageReceived(android::sp<android::AMessage> const&) frameworks/av/include/media/stagefright/foundation/AHandlerReflector.h:35:13\n\n    #10 0xaf9f37d5 in android::AHandler::deliverMessage(android::sp<android::AMessage> const&) frameworks/av/media/libstagefright/foundation/AHandler.cpp:27:5\n\n    #11 0xaf9f5b35 in android::AMessage::deliver() frameworks/av/media/libstagefright/foundation/AMessage.cpp:382:5\n\n    #12 0xaf9f440b in android::ALooper::loop() frameworks/av/media/libstagefright/foundation/ALooper.cpp:220:5\n\n    #13 0xaf82da85 in android::Thread::_threadLoop(void*) system/core/libutils/Threads.cpp:754:22\n\n    #14 0xaef376c3 in __pthread_start(void*) bionic/libc/bionic/pthread_create.cpp:198:18\n\n    #15 0xaef091cf in __start_thread bionic/libc/bionic/clone.cpp:41:16\n\n\n\n0xac80d400 is located 0 bytes inside of 64-byte region [0xac80d400,0xac80d440)\n\nfreed by thread T27 (NuCachedSource2) here:\n\n    #0 0xaf04a90f in __interceptor_free\n\n    #1 0xaf9f966b in android::AString::clear() frameworks/av/media/libstagefright/foundation/AString.cpp:129:9\n\n\n\npreviously allocated by thread T26 (generic) here:\n\n    #0 0xaf04afff in __interceptor_realloc\n\n    #1 0xaf9f986b in android::AString::append(char const*, unsigned int) frameworks/av/media/libstagefright/foundation/AString.cpp:195:25\n\n\n\nThread T27 (NuCachedSource2) created by T26 (generic) here:\n\n    #0 0xaf0324db in pthread_create\n\n    #1 0xaf82d641 in androidCreateRawThreadEtc system/core/libutils/Threads.cpp:160:18\n\n\n\nThread T26 (generic) created by T25 (NuPlayerDriver ) here:\n\n    #0 0xaf0324db in pthread_create\n\n    #1 0xaf82d641 in androidCreateRawThreadEtc system/core/libutils/Threads.cpp:160:18\n\n\n\nThread T25 (NuPlayerDriver ) created by T2 (Binder:378_2) here:\n\n    #0 0xaf0324db in pthread_create\n\n    #1 0xaf82d641 in androidCreateRawThreadEtc system/core/libutils/Threads.cpp:160:18\n\n\n\nThread T2 (Binder:378_2) created by T1 (Binder:378_1) here:\n\n    #0 0xaf0324db in pthread_create\n\n    #1 0xaf82d641 in androidCreateRawThreadEtc system/core/libutils/Threads.cpp:160:18\n\n\n\nThread T1 (Binder:378_1) created by T0 here:\n\n    #0 0xaf0324db in pthread_create\n\n    #1 0xaf82d641 in androidCreateRawThreadEtc system/core/libutils/Threads.cpp:160:18\n\n    #2 0xaef061b1 in __libc_init bionic/libc/bionic/libc_init_dynamic.cpp:109:8\n\n    #3 0xffffffff  (<unknown module>)\n\n\n\nSUMMARY: AddressSanitizer: heap-use-after-free (/system/lib/libclang_rt.asan-arm-android.so+0x60287)\n\nShadow bytes around the buggy address:\n  0x15901a30: fa fa fa fa fa fa fa fa fa fa fa fa fa fa fa fa\n  0x15901a40: fa fa fa fa 00 00 00 00 00 00 00 00 fa fa fa fa\n  0x15901a50: 00 00 00 00 00 00 04 fa fa fa fa fa 00 00 00 00\n  0x15901a60: 00 00 04 fa fa fa fa fa 00 00 00 00 00 00 00 fa\n  0x15901a70: fa fa fa fa fd fd fd fd fd fd fd fd fa fa fa fa\n=>0x15901a80:[fd]fd fd fd fd fd fd fd fa fa fa fa fd fd fd fd\n  0x15901a90: fd fd fd fd fa fa fa fa 00 00 00 00 00 00 00 04\n  0x15901aa0: fa fa fa fa 00 00 00 00 00 00 02 fa fa fa fa fa\n  0x15901ab0: fd fd fd fd fd fd fd fd fa fa fa fa 00 00 00 00\n  0x15901ac0: 00 00 00 04 fa fa fa fa fd fd fd fd fd fd fd fd\n  0x15901ad0: fa fa fa fa fd fd fd fd fd fd fd fd fa fa fa fa\nShadow byte legend (one shadow byte represents 8 application bytes):\n  Addressable:           00\n  Partially addressable: 01 02 03 04 05 06 07\n  Heap left redzone:       fa\n  Heap right redzone:      fb\n  Freed heap region:       fd\n  Stack left redzone:      f1\n  Stack mid redzone:       f2\n  Stack right redzone:     f3\n  Stack partial redzone:   f4\n  Stack after return:      f5\n  Stack use after scope:   f8\n  Global redzone:          f9\n  Global init order:       f6\n  Poisoned by user:        f7\n  Container overflow:      fc\n  Array cookie:            ac\n  Intra object redzone:    bb\n  ASan internal:           fe\n  Left alloca redzone:     ca\n  Right alloca redzone:    cb\n\n==378==ABORTING\n\n--------- ServiceManager (284):\nservice 'media.resource_manager' died\nservice 'media.player' died\n--------- IMediaDeathNotifier (5901):\nmedia server died\nerror (100, 0)\nError (100,0)\n--------- mediaserver (5950):\nServiceManager: 0xab607e40",
  "sanitizer": "AddressSanitizer",
  "summary": "AddressSanitizer: heap-use-after-free (/system/lib/libclang_rt.asan-arm-android.so+0x60287)",
  "fault_type": "heap-use-after-free",
  "call_stack": [
    "#0 0xaf036287 in strlen"
  ],
  "full_stack_details": [
    {
      "line": "#0 0xaf036287 in strlen",
      "address": 2936234631,
      "module_path": "strlen"
    }
  ],
  "minimized_stack_details": [
    {
      "line": "#0 0xaf036287 in strlen",
      "address": 2936234631,
      "module_path": "strlen"
    }
  ]
}
