{
  "text": "==336==ERROR: AddressSanitizer: stack-buffer-overflow on address 0x00201b12d49f at pc 0x7ff6bfabe9d9 bp 0x00201b12d2a0 sp 0x00201b12d2e8\nREAD of size 1 at 0x00201b12d49f thread T0\nSCARINESS: 27 (1-byte-read-stack-buffer-overflow)\n    #0 0x7ff6bfabe9d8 in v8::internal::`anonymous namespace'::GenerateSourceString C:\\b\\s\\w\\ir\\cache\\builder\\src\\v8\\test\\fuzzer\\regexp-builtins.cc:294:25\n    #1 0x7ff6bfaa3909 in LLVMFuzzerTestOneInput C:\\b\\s\\w\\ir\\cache\\builder\\src\\v8\\test\\fuzzer\\regexp-builtins.cc:442:3\n    #2 0x7ff6bfae1203 in fuzzer::Fuzzer::ExecuteCallback(unsigned char const *,unsigned __int64) C:\\b\\s\\w\\ir\\cache\\builder\\src\\third_party\\libFuzzer\\src\\FuzzerLoop.cpp:570\n    #3 0x7ff6bfad77b5 in fuzzer::RunOneTest(class fuzzer::Fuzzer *,char const *,unsigned __int64) C:\\b\\s\\w\\ir\\cache\\builder\\src\\third_party\\libFuzzer\\src\\FuzzerDriver.cpp:280\n    #4 0x7ff6bfadab6e in fuzzer::FuzzerDriver(int *,char * * *,int (*)(unsigned char const *,unsigned __int64)) C:\\b\\s\\w\\ir\\cache\\builder\\src\\third_party\\libFuzzer\\src\\FuzzerDriver.cpp:713\n    #5 0x7ff6bfae71cc in main C:\\b\\s\\w\\ir\\cache\\builder\\src\\third_party\\libFuzzer\\src\\FuzzerMain.cpp:20\n    #6 0x7ff6c2f1f0d3 in __scrt_common_main_seh f:\\dd\\vctools\\crt\\vcstartup\\src\\startup\\exe_common.inl:283\n    #7 0x7ffef0608363 in BaseThreadInitThunk (C:\\Windows\\System32\\KERNEL32.DLL+0x180008363)\n    #8 0x7ffef22d7090 in RtlUserThreadStart (C:\\Windows\\SYSTEM32\\ntdll.dll+0x180067090)\n\nAddress 0x00201b12d49f is located in stack of thread T0 at offset 383 in frame\n    #0 0x7ff6bfabc36f in v8::internal::`anonymous namespace'::GenerateSourceString C:\\b\\s\\w\\ir\\cache\\builder\\src\\v8\\test\\fuzzer\\regexp-builtins.cc:290\n\n  This frame has 8 object(s):\n    [32, 64) 'ref.tmp.i58' (line 210)\n    [96, 102) 'buffer.i' (line 252)\n    [128, 160) 'ref.tmp.i' (line 194)\n    [192, 224) 'pattern' (line 291)\n    [256, 288) 'flags' (line 292)\n    [320, 352) 'last_index' (line 293)\n    [384, 416) 'subject' (line 294) <== Memory access at offset 383 underflows this variable\n    [448, 696) 'ss' (line 297)\nHINT: this may be a false positive if your program uses some custom stack unwind mechanism, swapcontext or vfork\n      (longjmp, SEH and C++ exceptions *are* supported)\nSUMMARY: AddressSanitizer: stack-buffer-overflow C:\\b\\s\\w\\ir\\cache\\builder\\src\\v8\\test\\fuzzer\\regexp-builtins.cc:294:25 in v8::internal::`anonymous namespace'::GenerateSourceString\nShadow bytes around the buggy address:\n  0x01a5ca825a40: 00 00 00 00 00 00 00 00 00 00 00 00 00 00 00 00\n  0x01a5ca825a50: 00 00 00 00 00 00 00 00 00 00 00 00 00 00 00 00\n  0x01a5ca825a60: 00 00 00 00 f1 f1 f1 f1 00 00 00 00 f2 f2 f2 f2\n  0x01a5ca825a70: f8 f2 f2 f2 f8 f8 f8 f8 f2 f2 f2 f2 00 00 00 00\n  0x01a5ca825a80: f2 f2 f2 f2 00 00 00 00 f2 f2 f2 f2 00 00 00 00\n=>0x01a5ca825a90: f2 f2 f2[f2]00 00 00 00 f2 f2 f2 f2 f8 f8 f8 f8\n  0x01a5ca825aa0: f8 f8 f8 f8 f8 f8 f8 f8 f8 f8 f8 f8 f8 f8 f8 f8\n  0x01a5ca825ab0: f8 f8 f8 f8 f8 f8 f8 f8 f8 f8 f8 f3 f3 f3 f3 f3\n  0x01a5ca825ac0: f3 f3 f3 f3 00 00 00 00 00 00 00 00 00 00 00 00\n  0x01a5ca825ad0: 00 00 00 00 00 00 00 00 00 00 00 00 00 00 00 00\n  0x01a5ca825ae0: 00 00 00 00 00 00 00 00 00 00 00 00 00 00 00 00\nShadow byte legend (one shadow byte represents 8 application bytes):\n  Addressable:           00\n  Partially addressable: 01 02 03 04 05 06 07\n  Heap left redzone:       fa\n  Freed heap region:       fd\n  Stack left redzone:      f1\n  Stack mid redzone:       f2\n  Stack right redzone:     f3\n  Stack after return:      f5\n  Stack use after scope:   f8\n  Global redzone:          f9\n  Global init order:       f6\n  Poisoned by user:        f7\n  Container overflow:      fc\n  Array cookie:            ac\n  Intra object redzone:    bb\n  ASan internal:           fe\n  Left alloca redzone:     ca\n  Right alloca redzone:    cb\n  Shadow gap:              cc\n==336==ABORTING\n",
  "sanitizer": "AddressSanitizer",
  "summary": "AddressSanitizer: stack-buffer-overflow C:\\b\\s\\w\\ir\\cache\\builder\\src\\v8\\test\\fuzzer\\regexp-builtins.cc:294:25 in v8::internal::`anonymous namespace'::GenerateSourceString",
  "fault_type": "stack-buffer-overflow",
  "call_stack": [
    "#0 0x7ff6bfabe9d8 in v8::internal::`anonymous namespace'::GenerateSourceString C:\\b\\s\\w\\ir\\cache\\builder\\src\\v8\\test\\fuzzer\\regexp-builtins.cc:294:25",
    "#1 0x7ff6bfaa3909 in LLVMFuzzerTestOneInput C:\\b\\s\\w\\ir\\cache\\builder\\src\\v8\\test\\fuzzer\\regexp-builtins.cc:442:3",
    "#2 0x7ff6bfae1203 in fuzzer::Fuzzer::ExecuteCallback(unsigned char const *,unsigned __int64) C:\\b\\s\\w\\ir\\cache\\builder\\src\\third_party\\libFuzzer\\src\\FuzzerLoop.cpp:570",
    "#3 0x7ff6bfad77b5 in fuzzer::RunOneTest(class fuzzer::Fuzzer *,char const *,unsigned __int64) C:\\b\\s\\w\\ir\\cache\\builder\\src\\third_party\\libFuzzer\\src\\FuzzerDriver.cpp:280",
    "#4 0x7ff6bfadab6e in fuzzer::FuzzerDriver(int *,char * * *,int (*)(unsigned char const *,unsigned __int64)) C:\\b\\s\\w\\ir\\cache\\builder\\src\\third_party\\libFuzzer\\src\\FuzzerDriver.cpp:713",
    "#5 0x7ff6bfae71cc in main C:\\b\\s\\w\\ir\\cache\\builder\\src\\third_party\\libFuzzer\\src\\FuzzerMain.cpp:20",
    "#6 0x7ff6c2f1f0d3 in __scrt_common_main_seh f:\\dd\\vctools\\crt\\vcstartup\\src\\startup\\exe_common.inl:283",
    "#7 0x7ffef0608363 in BaseThreadInitThunk (C:\\Windows\\System32\\KERNEL32.DLL+0x180008363)",
    "#8 0x7ffef22d7090 in RtlUserThreadStart (C:\\Windows\\SYSTEM32\\ntdll.dll+0x180067090)"
  ],
  "full_stack_details": [
    {
      "line": "#0 0x7ff6bfabe9d8 in v8::internal::`anonymous namespace'::GenerateSourceString C:\\b\\s\\w\\ir\\cache\\builder\\src\\v8\\test\\fuzzer\\regexp-builtins.cc:294:25",
      "address": 140697754397144,
      "function_name": "v8::internal::`anonymous namespace'::GenerateSourceString",
      "function_offset": 25,
      "source_file_name": "regexp-builtins.cc",
      "source_file_path": "C:\\b\\s\\w\\ir\\cache\\builder\\src\\v8\\test\\fuzzer\\regexp-builtins.cc",
      "source_file_line": 294
    },
    {
      "line": "#1 0x7ff6bfaa3909 in LLVMFuzzerTestOneInput C:\\b\\s\\w\\ir\\cache\\builder\\src\\v8\\test\\fuzzer\\regexp-builtins.cc:442:3",
      "address": 140697754286345,
      "function_name": "LLVMFuzzerTestOneInput",
      "function_offset": 3,
      "source_file_name": "regexp-builtins.cc",
      "source_file_path": "C:\\b\\s\\w\\ir\\cache\\builder\\src\\v8\\test\\fuzzer\\regexp-builtins.cc",
      "source_file_line": 442
    },
    {
      "line": "#2 0x7ff6bfae1203 in fuzzer::Fuzzer::ExecuteCallback(unsigned char const *,unsigned __int64) C:\\b\\s\\w\\ir\\cache\\builder\\src\\third_party\\libFuzzer\\src\\FuzzerLoop.cpp:570",
      "address": 140697754538499,
      "function_name": "fuzzer::Fuzzer::ExecuteCallback(unsigned char const *,unsigned __int64)",
      "source_file_name": "FuzzerLoop.cpp",
      "source_file_path": "C:\\b\\s\\w\\ir\\cache\\builder\\src\\third_party\\libFuzzer\\src\\FuzzerLoop.cpp",
      "source_file_line": 570
    },
    {
      "line": "#3 0x7ff6bfad77b5 in fuzzer::RunOneTest(class fuzzer::Fuzzer *,char const *,unsigned __int64) C:\\b\\s\\w\\ir\\cache\\builder\\src\\third_party\\libFuzzer\\src\\FuzzerDriver.cpp:280",
      "address": 140697754498997,
      "function_name": "fuzzer::RunOneTest(class fuzzer::Fuzzer *,char const *,unsigned __int64)",
      "source_file_name": "FuzzerDriver.cpp",
      "source_file_path": "C:\\b\\s\\w\\ir\\cache\\builder\\src\\third_party\\libFuzzer\\src\\FuzzerDriver.cpp",
      "source_file_line": 280
    },
    {
      "line": "#4 0x7ff6bfadab6e in fuzzer::FuzzerDriver(int *,char * * *,int (*)(unsigned char const *,unsigned __int64)) C:\\b\\s\\w\\ir\\cache\\builder\\src\\third_party\\libFuzzer\\src\\FuzzerDriver.cpp:713",
      "address": 140697754512238,
      "function_name": "fuzzer::FuzzerDriver(int *,char * * *,int (*)(unsigned char const *,unsigned __int64))",
      "source_file_name": "FuzzerDriver.cpp",
      "source_file_path": "C:\\b\\s\\w\\ir\\cache\\builder\\src\\third_party\\libFuzzer\\src\\FuzzerDriver.cpp",
      "source_file_line": 713
    },
    {
      "line": "#5 0x7ff6bfae71cc in main C:\\b\\s\\w\\ir\\cache\\builder\\src\\third_party\\libFuzzer\\src\\FuzzerMain.cpp:20",
      "address": 140697754563020,
      "function_name": "main",
      "source_file_name": "FuzzerMain.cpp",
      "source_file_path": "C:\\b\\s\\w\\ir\\cache\\builder\\src\\third_party\\libFuzzer\\src\\FuzzerMain.cpp",
      "source_file_line": 20
    },
    {
      "line": "#6 0x7ff6c2f1f0d3 in __scrt_common_main_seh f:\\dd\\vctools\\crt\\vcstartup\\src\\startup\\exe_common.inl:283",
      "address": 140697809318099,
      "function_name": "__scrt_common_main_seh",
      "source_file_name": "exe_common.inl",
      "source_file_path": "f:\\dd\\vctools\\crt\\vcstartup\\src\\startup\\exe_common.inl",
      "source_file_line": 283
    },
    {
      "line": "#7 0x7ffef0608363 in BaseThreadInitThunk (C:\\Windows\\System32\\KERNEL32.DLL+0x180008363)",
      "address": 140732931277667,
      "function_name": "BaseThreadInitThunk",
      "module_path": "C:\\Windows\\System32\\KERNEL32.DLL",
      "module_offset": 6442484579
    },
    {
      "line": "#8 0x7ffef22d7090 in RtlUserThreadStart (C:\\Windows\\SYSTEM32\\ntdll.dll+0x180067090)",
      "address": 140732961484944,
      "function_name": "RtlUserThreadStart",
      "module_path": "C:\\Windows\\SYSTEM32\\ntdll.dll",
      "module_offset": 6442872976
    }
  ],
  "full_stack_names": [
    "v8::internal::`anonymous namespace'::GenerateSourceString",
    "LLVMFuzzerTestOneInput",
    "fuzzer::Fuzzer::ExecuteCallback(unsigned char const *,unsigned __int64)",
    "fuzzer::RunOneTest(class fuzzer::Fuzzer *,char const *,unsigned __int64)",
    "fuzzer::FuzzerDriver(int *,char * * *,int (*)(unsigned char const *,unsigned __int64))",
    "main",
    "__scrt_common_main_seh",
    "BaseThreadInitThunk",
    "RtlUserThreadStart"
  ],
  "minimized_stack_details": [
    {
      "line": "#0 0x7ff6bfabe9d8 in v8::internal::`anonymous namespace'::GenerateSourceString C:\\b\\s\\w\\ir\\cache\\builder\\src\\v8\\test\\fuzzer\\regexp-builtins.cc:294:25",
      "address": 140697754397144,
      "function_name": "v8::internal::`anonymous namespace'::GenerateSourceString",
      "function_offset": 25,
      "source_file_name": "regexp-builtins.cc",
      "source_file_path": "C:\\b\\s\\w\\ir\\cache\\builder\\src\\v8\\test\\fuzzer\\regexp-builtins.cc",
      "source_file_line": 294
    },
    {
      "line": "#1 0x7ff6bfaa3909 in LLVMFuzzerTestOneInput C:\\b\\s\\w\\ir\\cache\\builder\\src\\v8\\test\\fuzzer\\regexp-builtins.cc:442:3",
      "address": 140697754286345,
      "function_name": "regexp-builtins.cc",
      "function_offset": 3,
      "source_file_name": "regexp-builtins.cc",
      "source_file_path": "C:\\b\\s\\w\\ir\\cache\\builder\\src\\v8\\test\\fuzzer\\regexp-builtins.cc",
      "source_file_line": 442
    }
  ],
  "minimized_stack": [
    "v8::internal::`anonymous namespace'::GenerateSourceString",
    "regexp-builtins.cc"
  ],
  "minimized_stack_function_names": [
    "v8::internal::`anonymous namespace'::GenerateSourceString",
    "regexp-builtins.cc"
  ],
  "scariness_score": 27,
  "scariness_description": "1-byte-read-stack-buffer-overflow"
}
